django_mqueue-0.20.0.dist-info/licenses/LICENSE
docsite/src/assets/py/init.py
docsite/src/assets/py/events/fields_autoguess.py
docsite/src/assets/py/events/models.py
docsite/src/assets/py/events/parameters.py
docsite/src/assets/py/events/query.py
docsite/src/assets/py/events/query2.py
docsite/src/assets/py/events/query3.py
docsite/src/assets/py/get_started/date.py
docsite/src/assets/py/get_started/qs.py
mqueue/__init__.py
mqueue/admin.py
mqueue/apps.py
mqueue/conf.py
mqueue/handlers.py
mqueue/logging.py
mqueue/mcpserver.py
mqueue/models.py
mqueue/resources.py
mqueue/signals.py
mqueue/tracking.py
mqueue/urls.py
mqueue/utils.py
mqueue/watchers.py
mqueue/hooks/__init__.py
mqueue/hooks/redis/__init__.py
mqueue/hooks/redis/serializer.py
mqueue/locale/fr/LC_MESSAGES/django.mo
mqueue/locale/fr/LC_MESSAGES/django.po
mqueue/migrations/0001_initial.py
mqueue/migrations/0002_alter_mevent_id.py
mqueue/migrations/__init__.py
mqueue/static/mqueue/mqueue.css
mqueue/tests/__init__.py
mqueue/tests/base.py
mqueue/tests/runtests.py
mqueue/tests/test_admin.py
mqueue/tests/test_apps.py
mqueue/tests/test_create.py
mqueue/tests/test_hooks.py
mqueue/tests/test_logging.py
mqueue/tests/test_managers.py
mqueue/tests/test_signals.py
mqueue/tests/test_utils.py
mqueue/tests/test_watchers.py
mqueue/tests/urls.py
mqueue/tests/hooks/__init__.py
mqueue/tests/hooks/redis.py
django_mqueue-0.20.0.dist-info/METADATA
django_mqueue-0.20.0.dist-info/WHEEL
django_mqueue-0.20.0.dist-info/top_level.txt
django_mqueue-0.20.0.dist-info/RECORD
