Metadata-Version: 2.4
Name: django-mqueue
Version: 0.20.0
Summary: Events queue for Django
Home-page: https://github.com/synw/django-mqueue
Download-URL: https://github.com/synw/django-mqueue/releases/tag/0.20.0
Author: synw
Author-email: synwe@yahoo.com
License: MIT
Keywords: django,logging,monitoring
Classifier: Development Status :: 4 - Beta
Classifier: Framework :: Django :: 1.11
Classifier: Intended Audience :: Developers
Classifier: Programming Language :: Python :: 3.8
License-File: LICENSE
Requires-Dist: django-mcpx
Requires-Dist: django-import-export
Dynamic: author
Dynamic: author-email
Dynamic: classifier
Dynamic: description
Dynamic: description-content-type
Dynamic: download-url
Dynamic: home-page
Dynamic: keywords
Dynamic: license
Dynamic: license-file
Dynamic: requires-dist
Dynamic: summary
